{
  "organism_id": "organism_001",
  "created_at": "2024-01-01T00:00:00Z",
  "total_trades": 60,
  "win_trades": 47,
  "loss_trades": 13,
  "total_profit": 1880.0,
  "total_loss": 260.0,
  "win_rate": 0.7833333333333333,
  "best_strategy": null,
  "market_patterns": [],
  "trade_history": [
    {
      "time": "2026-03-14T07:19:00.275491",
      "signal": "BUY",
      "profit": -20.0,
      "strategy": "RSI=100.0 MACD bullish"
    },
    {
      "time": "2026-03-14T07:19:00.277306",
      "signal": "BUY",
      "profit": 40.0,
      "strategy": "RSI=100.0 MACD bullish"
    },
    {
      "time": "2026-03-14T07:19:00.278915",
      "signal": "BUY",
      "profit": 40.0,
      "strategy": "RSI=100.0 MACD bullish"
    },
    {
      "time": "2026-03-14T07:19:00.280588",
      "signal": "BUY",
      "profit": 40.0,
      "strategy": "RSI=100.0 MACD bullish"
    },
    {
      "time": "2026-03-14T07:19:00.282350",
      "signal": "BUY",
      "profit": 40.0,
      "strategy": "RSI=100.0 MACD bullish"
    },
    {
      "time": "2026-03-14T07:19:00.284014",
      "signal": "BUY",
      "profit": 40.0,
      "strategy": "RSI=100.0 MACD bullish"
    },
    {
      "time": "2026-03-14T07:19:00.285878",
      "signal": "BUY",
      "profit": 40.0,
      "strategy": "RSI=100.0 MACD bullish"
    },
    {
      "time": "2026-03-14T07:19:00.287511",
      "signal": "BUY",
      "profit": 40.0,
      "strategy": "RSI=100.0 MACD bullish"
    },
    {
      "time": "2026-03-14T07:19:00.289198",
      "signal": "BUY",
      "profit": 40.0,
      "strategy": "RSI=100.0 MACD bullish"
    },
    {
      "time": "2026-03-14T07:19:00.291110",
      "signal": "BUY",
      "profit": 40.0,
      "strategy": "RSI=100.0 MACD bullish"
    },
    {
      "time": "2026-03-14T07:19:00.292799",
      "signal": "BUY",
      "profit": -20.0,
      "strategy": "RSI=100.0 MACD bullish"
    },
    {
      "time": "2026-03-14T07:19:00.294566",
      "signal": "BUY",
      "profit": -20.0,
      "strategy": "RSI=100.0 MACD bullish"
    },
    {
      "time": "2026-03-14T07:19:00.296523",
      "signal": "BUY",
      "profit": 40.0,
      "strategy": "RSI=100.0 MACD bullish"
    },
    {
      "time": "2026-03-14T07:19:00.298253",
      "signal": "BUY",
      "profit": 40.0,
      "strategy": "RSI=100.0 MACD bullish"
    },
    {
      "time": "2026-03-14T07:19:00.300805",
      "signal": "BUY",
      "profit": 40.0,
      "strategy": "RSI=100.0 MACD bullish"
    },
    {
      "time": "2026-03-14T07:19:00.302591",
      "signal": "BUY",
      "profit": -20.0,
      "strategy": "RSI=100.0 MACD bullish"
    },
    {
      "time": "2026-03-14T07:19:00.304394",
      "signal": "BUY",
      "profit": 40.0,
      "strategy": "RSI=100.0 MACD bullish"
    },
    {
      "time": "2026-03-14T07:19:00.306203",
      "signal": "BUY",
      "profit": -20.0,
      "strategy": "RSI=100.0 MACD bullish"
    },
    {
      "time": "2026-03-14T07:19:00.308293",
      "signal": "BUY",
      "profit": 40.0,
      "strategy": "RSI=100.0 MACD bullish"
    },
    {
      "time": "2026-03-14T07:19:00.310305",
      "signal": "BUY",
      "profit": 40.0,
      "strategy": "RSI=100.0 MACD bullish"
    },
    {
      "time": "2026-03-15T05:02:39.900411",
      "signal": "BUY",
      "profit": 40.0,
      "strategy": "RSI=100.0 MACD bullish"
    },
    {
      "time": "2026-03-15T05:02:39.902991",
      "signal": "BUY",
      "profit": 40.0,
      "strategy": "RSI=100.0 MACD bullish"
    },
    {
      "time": "2026-03-15T05:02:39.905523",
      "signal": "BUY",
      "profit": 40.0,
      "strategy": "RSI=100.0 MACD bullish"
    },
    {
      "time": "2026-03-15T05:02:39.907986",
      "signal": "BUY",
      "profit": -20.0,
      "strategy": "RSI=100.0 MACD bullish"
    },
    {
      "time": "2026-03-15T05:02:39.910597",
      "signal": "BUY",
      "profit": 40.0,
      "strategy": "RSI=100.0 MACD bullish"
    },
    {
      "time": "2026-03-15T05:02:39.912975",
      "signal": "BUY",
      "profit": -20.0,
      "strategy": "RSI=100.0 MACD bullish"
    },
    {
      "time": "2026-03-15T05:02:39.915668",
      "signal": "BUY",
      "profit": 40.0,
      "strategy": "RSI=100.0 MACD bullish"
    },
    {
      "time": "2026-03-15T05:02:39.918128",
      "signal": "BUY",
      "profit": -20.0,
      "strategy": "RSI=100.0 MACD bullish"
    },
    {
      "time": "2026-03-15T05:02:39.920836",
      "signal": "BUY",
      "profit": 40.0,
      "strategy": "RSI=100.0 MACD bullish"
    },
    {
      "time": "2026-03-15T05:02:39.923332",
      "signal": "BUY",
      "profit": 40.0,
      "strategy": "RSI=100.0 MACD bullish"
    },
    {
      "time": "2026-03-15T05:02:39.925934",
      "signal": "BUY",
      "profit": 40.0,
      "strategy": "RSI=100.0 MACD bullish"
    },
    {
      "time": "2026-03-15T05:02:39.929516",
      "signal": "BUY",
      "profit": 40.0,
      "strategy": "RSI=100.0 MACD bullish"
    },
    {
      "time": "2026-03-15T05:02:39.937375",
      "signal": "BUY",
      "profit": 40.0,
      "strategy": "RSI=100.0 MACD bullish"
    },
    {
      "time": "2026-03-15T05:02:39.940279",
      "signal": "BUY",
      "profit": 40.0,
      "strategy": "RSI=100.0 MACD bullish"
    },
    {
      "time": "2026-03-15T05:02:39.942957",
      "signal": "BUY",
      "profit": -20.0,
      "strategy": "RSI=100.0 MACD bullish"
    },
    {
      "time": "2026-03-15T05:02:39.945573",
      "signal": "BUY",
      "profit": 40.0,
      "strategy": "RSI=100.0 MACD bullish"
    },
    {
      "time": "2026-03-15T05:02:39.948427",
      "signal": "BUY",
      "profit": 40.0,
      "strategy": "RSI=100.0 MACD bullish"
    },
    {
      "time": "2026-03-15T05:02:39.951066",
      "signal": "BUY",
      "profit": 40.0,
      "strategy": "RSI=100.0 MACD bullish"
    },
    {
      "time": "2026-03-15T05:02:39.953737",
      "signal": "BUY",
      "profit": 40.0,
      "strategy": "RSI=100.0 MACD bullish"
    },
    {
      "time": "2026-03-15T05:02:39.956761",
      "signal": "BUY",
      "profit": 40.0,
      "strategy": "RSI=100.0 MACD bullish"
    },
    {
      "time": "2026-03-16T05:12:07.432277",
      "signal": "BUY",
      "profit": 40.0,
      "strategy": "RSI=100.0 MACD bullish"
    },
    {
      "time": "2026-03-16T05:12:07.435883",
      "signal": "BUY",
      "profit": 40.0,
      "strategy": "RSI=100.0 MACD bullish"
    },
    {
      "time": "2026-03-16T05:12:07.439523",
      "signal": "BUY",
      "profit": -20.0,
      "strategy": "RSI=100.0 MACD bullish"
    },
    {
      "time": "2026-03-16T05:12:07.443229",
      "signal": "BUY",
      "profit": 40.0,
      "strategy": "RSI=100.0 MACD bullish"
    },
    {
      "time": "2026-03-16T05:12:07.446736",
      "signal": "BUY",
      "profit": 40.0,
      "strategy": "RSI=100.0 MACD bullish"
    },
    {
      "time": "2026-03-16T05:12:07.450516",
      "signal": "BUY",
      "profit": 40.0,
      "strategy": "RSI=100.0 MACD bullish"
    },
    {
      "time": "2026-03-16T05:12:07.454350",
      "signal": "BUY",
      "profit": 40.0,
      "strategy": "RSI=100.0 MACD bullish"
    },
    {
      "time": "2026-03-16T05:12:07.457992",
      "signal": "BUY",
      "profit": -20.0,
      "strategy": "RSI=100.0 MACD bullish"
    },
    {
      "time": "2026-03-16T05:12:07.462447",
      "signal": "BUY",
      "profit": 40.0,
      "strategy": "RSI=100.0 MACD bullish"
    },
    {
      "time": "2026-03-16T05:12:07.466111",
      "signal": "BUY",
      "profit": 40.0,
      "strategy": "RSI=100.0 MACD bullish"
    },
    {
      "time": "2026-03-16T05:12:07.470061",
      "signal": "BUY",
      "profit": -20.0,
      "strategy": "RSI=100.0 MACD bullish"
    },
    {
      "time": "2026-03-16T05:12:07.473757",
      "signal": "BUY",
      "profit": 40.0,
      "strategy": "RSI=100.0 MACD bullish"
    },
    {
      "time": "2026-03-16T05:12:07.477453",
      "signal": "BUY",
      "profit": 40.0,
      "strategy": "RSI=100.0 MACD bullish"
    },
    {
      "time": "2026-03-16T05:12:07.481441",
      "signal": "BUY",
      "profit": 40.0,
      "strategy": "RSI=100.0 MACD bullish"
    },
    {
      "time": "2026-03-16T05:12:07.485205",
      "signal": "BUY",
      "profit": 40.0,
      "strategy": "RSI=100.0 MACD bullish"
    },
    {
      "time": "2026-03-16T05:12:07.489322",
      "signal": "BUY",
      "profit": 40.0,
      "strategy": "RSI=100.0 MACD bullish"
    },
    {
      "time": "2026-03-16T05:12:07.493209",
      "signal": "BUY",
      "profit": 40.0,
      "strategy": "RSI=100.0 MACD bullish"
    },
    {
      "time": "2026-03-16T05:12:07.497344",
      "signal": "BUY",
      "profit": 40.0,
      "strategy": "RSI=100.0 MACD bullish"
    },
    {
      "time": "2026-03-16T05:12:07.501246",
      "signal": "BUY",
      "profit": 40.0,
      "strategy": "RSI=100.0 MACD bullish"
    },
    {
      "time": "2026-03-16T05:12:07.505453",
      "signal": "BUY",
      "profit": -20.0,
      "strategy": "RSI=100.0 MACD bullish"
    }
  ]
}